pytrendsdaily/__init__.py
pytrendsdaily/dailydata.py
pytrendsdaily-1.0.0.dist-info/LICENSE
pytrendsdaily-1.0.0.dist-info/METADATA
pytrendsdaily-1.0.0.dist-info/WHEEL
pytrendsdaily-1.0.0.dist-info/top_level.txt
pytrendsdaily-1.0.0.dist-info/RECORD
