Metadata-Version: 2.1
Name: pytrendsdaily
Version: 1.0.0
Summary: Fetches Daily Data from Google Trends.
Home-page: http://github.com/salompas/pytrendsdaily
Author: Guilherme Salome
Author-email: guilhermesalome@gmail.com
License: MIT
Platform: UNKNOWN
Classifier: Programming Language :: Python :: 3.6
Classifier: License :: OSI Approved :: MIT License
Classifier: Operating System :: OS Independent
Classifier: Development Status :: 3 - Alpha
Requires-Dist: pandas (>=0.23.0)
Requires-Dist: pytrends (>=4.4.0)
